flow_judge/__init__.py
flow_judge/eval_data_types.py
flow_judge/flow_judge.py
flow_judge/integrations/__init__.py
flow_judge/integrations/haystack.py
flow_judge/integrations/langchain.py
flow_judge/integrations/llama_index.py
flow_judge/metrics/__init__.py
flow_judge/metrics/metric.py
flow_judge/metrics/presets.py
flow_judge/models/__init__.py
flow_judge/models/baseten.py
flow_judge/models/common.py
flow_judge/models/huggingface.py
flow_judge/models/llamafile.py
flow_judge/models/vllm.py
flow_judge/models/adapters/base.py
flow_judge/models/adapters/baseten/README.md
flow_judge/models/adapters/baseten/adapter.py
flow_judge/models/adapters/baseten/api_auth.py
flow_judge/models/adapters/baseten/data_io.py
flow_judge/models/adapters/baseten/deploy.py
flow_judge/models/adapters/baseten/errors.py
flow_judge/models/adapters/baseten/gpu.py
flow_judge/models/adapters/baseten/management.py
flow_judge/models/adapters/baseten/token_bucket.py
flow_judge/models/adapters/baseten/util.py
flow_judge/models/adapters/baseten/validation.py
flow_judge/models/adapters/baseten/webhook.py
flow_judge/models/adapters/baseten/deployment/config.yaml
flow_judge/models/adapters/baseten/deployment/model/__init__.py
flow_judge/models/adapters/baseten/deployment/model/helper.py
flow_judge/models/adapters/baseten/deployment/model/model.py
flow_judge/utils/__init__.py
flow_judge/utils/prompt_formatter.py
flow_judge/utils/result_writer.py
flow_judge/utils/validators.py
flow_judge-0.1.2.dist-info/LICENSE
flow_judge-0.1.2.dist-info/METADATA
flow_judge-0.1.2.dist-info/WHEEL
flow_judge-0.1.2.dist-info/top_level.txt
flow_judge-0.1.2.dist-info/RECORD
