Metadata-Version: 2.1
Name: flow-judge
Version: 0.1.2
Summary: A small yet powerful LM Judge
Author-email: Bernardo Garcia <bernardo@flow-ai.com>, Karolus Sariola <karolus@flow-ai.com>, Minaam Shahid <minaam@flow-ai.com>, Tiina Vaahtio <tiina@flow-ai.com>, Alex Wegrzyn <alex.wegrzyn@flow-ai.com>
License: Apache License
Project-URL: Homepage, https://github.com/flowaicom/flow-judge
Keywords: LM-judge,evaluation,LLMs,AI,benchmarking
Classifier: Programming Language :: Python :: 3
Classifier: License :: OSI Approved :: Apache Software License
Classifier: Operating System :: OS Independent
Requires-Python: >=3.10
License-File: LICENSE
Requires-Dist: pydantic>=2.9.1
Requires-Dist: requests>=2.32.3
Requires-Dist: hf-transfer>=0.1.1
Requires-Dist: ipykernel>=6.29.0
Requires-Dist: ipywidgets>=8.1.0
Requires-Dist: tqdm>=4.66.1
Requires-Dist: structlog
Provides-Extra: baseten
Requires-Dist: truss>=0.9.44; extra == "baseten"
Requires-Dist: openai>=1.51.0; extra == "baseten"
Requires-Dist: aiohttp>=3.10.5; extra == "baseten"
Provides-Extra: dev
Requires-Dist: pytest; extra == "dev"
Requires-Dist: pre-commit; extra == "dev"
Requires-Dist: ruff; extra == "dev"
Requires-Dist: black; extra == "dev"
Requires-Dist: isort; extra == "dev"
Requires-Dist: pytest-cov; extra == "dev"
Requires-Dist: codecov; extra == "dev"
Requires-Dist: mypy>=1.11.2; extra == "dev"
Requires-Dist: types-requests; extra == "dev"
Requires-Dist: types-tqdm; extra == "dev"
Requires-Dist: memray>=1.14.0; extra == "dev"
Requires-Dist: pytest-memray>=1.7.0; extra == "dev"
Requires-Dist: pytest-asyncio<0.24.0,>=0.23.6; extra == "dev"
Requires-Dist: hypothesis; extra == "dev"
Provides-Extra: hf
Requires-Dist: transformers>=4.45.0; extra == "hf"
Requires-Dist: torch>=2.3.0; extra == "hf"
Requires-Dist: bitsandbytes<=0.42.0,>=0.41.0; extra == "hf"
Requires-Dist: accelerate>=0.34.2; extra == "hf"
Provides-Extra: integrations-test
Requires-Dist: llama-index; extra == "integrations-test"
Requires-Dist: llama-index-embeddings-huggingface; extra == "integrations-test"
Provides-Extra: llamafile
Requires-Dist: torch>=2.3.0; extra == "llamafile"
Requires-Dist: openai>=1.51.0; extra == "llamafile"
Provides-Extra: vllm
Requires-Dist: vllm==0.6.2; extra == "vllm"
